odoo8_addon_website_sale_checkout_comment-8.0.1.0.0-py2.7-nspkg.pth
odoo_addons/website_sale_checkout_comment/__openerp__.py
odoo_addons/website_sale_checkout_comment/__init__.py
odoo_addons/website_sale_checkout_comment/README.rst
odoo_addons/website_sale_checkout_comment/views/template.xml
odoo_addons/website_sale_checkout_comment/controllers/main.py
odoo_addons/website_sale_checkout_comment/controllers/__init__.py
odoo_addons/website_sale_checkout_comment/static/description/icon.png
odoo8_addon_website_sale_checkout_comment-8.0.1.0.0.dist-info/top_level.txt
odoo8_addon_website_sale_checkout_comment-8.0.1.0.0.dist-info/WHEEL
odoo8_addon_website_sale_checkout_comment-8.0.1.0.0.dist-info/RECORD
odoo8_addon_website_sale_checkout_comment-8.0.1.0.0.dist-info/metadata.json
odoo8_addon_website_sale_checkout_comment-8.0.1.0.0.dist-info/DESCRIPTION.rst
odoo8_addon_website_sale_checkout_comment-8.0.1.0.0.dist-info/METADATA
odoo8_addon_website_sale_checkout_comment-8.0.1.0.0.dist-info/namespace_packages.txt
